q-build/__init__.py
q-build/algorithms.py
q-build/circuit.py
q-build/gates.py
q-build/quantum_language.py
q-build/qubit.py
quan/__init__.py
quan/algorithms.py
quan/circuit.py
quan/gates.py
quan/quantum_language.py
quan/qubit.py
quanstructor/__init__.py
quanstructor/algorithms.py
quanstructor/circuit.py
quanstructor/gates.py
quanstructor/quantum_language.py
quanstructor/qubit.py
quan-0.1.dist-info/METADATA
quan-0.1.dist-info/WHEEL
quan-0.1.dist-info/top_level.txt
quan-0.1.dist-info/RECORD
